pygplib/__init__.py
pygplib/absexpr.py
pygplib/absfo.py
pygplib/absneg.py
pygplib/absprop.py
pygplib/baserelst.py
pygplib/be.py
pygplib/cnf.py
pygplib/constraints.py
pygplib/ecc.py
pygplib/fog.py
pygplib/grst.py
pygplib/name.py
pygplib/op.py
pygplib/prop.py
pygplib/symrelst.py
pygplib-2.3.2.dist-info/LICENSE
pygplib-2.3.2.dist-info/METADATA
pygplib-2.3.2.dist-info/WHEEL
pygplib-2.3.2.dist-info/RECORD
