Metadata-Version: 2.1
Name: pygplib
Version: 2.3.2
Summary: Python First-Order Graph Property Library
Home-page: https://github.com/toda-lab/pygplib
License: MIT
Keywords: logic,first-order-logic,graph,sat-solver,satisfiability
Author: Takahisa Toda
Author-email: pygplib+contact@gmail.com
Requires-Python: >=3.9,<4.0
Classifier: Development Status :: 3 - Alpha
Classifier: Intended Audience :: Science/Research
Classifier: License :: OSI Approved :: MIT License
Classifier: Operating System :: OS Independent
Classifier: Programming Language :: Python
Classifier: Programming Language :: Python :: 3
Classifier: Programming Language :: Python :: 3.9
Classifier: Programming Language :: Python :: 3.10
Classifier: Programming Language :: Python :: 3.11
Classifier: Programming Language :: Python :: 3 :: Only
Classifier: Topic :: Scientific/Engineering :: Artificial Intelligence
Classifier: Topic :: Scientific/Engineering :: Mathematics
Provides-Extra: docs
Provides-Extra: test
Requires-Dist: Sphinx (>=7.2.6,<8.0.0) ; extra == "docs"
Requires-Dist: argparse (>=1.4.0,<2.0.0) ; extra == "test"
Requires-Dist: pallets-sphinx-themes (>=2.1.1,<3.0.0) ; extra == "docs"
Requires-Dist: pyparsing (>=3.1.1,<4.0.0)
Requires-Dist: pytest (>=7.4.2,<8.0.0) ; extra == "test"
Requires-Dist: pytest-cov (>=4.1.0,<5.0.0) ; extra == "test"
Requires-Dist: python-sat (>=0.1.8.dev10,<0.2.0) ; extra == "test"
Requires-Dist: pyunigen (>=2.5.7,<3.0.0) ; extra == "test"
Requires-Dist: simpgraph (>=1.0.0,<2.0.0)
Requires-Dist: sphinx-removed-in (>=0.2.1,<0.3.0) ; extra == "docs"
Requires-Dist: sphinxcontrib-trio (>=1.1.2,<2.0.0) ; extra == "docs"
Requires-Dist: tox (>=4.11.3,<5.0.0) ; extra == "test"
Project-URL: Documentation, https://pygplib.readthedocs.io/en/latest/
Project-URL: Repository, https://github.com/toda-lab/pygplib
